araviq6/__init__.py
araviq6/array2qvideoframe.py
araviq6/labels.py
araviq6/py.typed
araviq6/qt_compat.py
araviq6/version.py
araviq6/videostream.py
araviq6/videowidgets.py
araviq6/samples/hello.jpg
araviq6/samples/hello.mp4
araviq6/tests/__init__.py
araviq6/tests/test_labels.py
araviq6/tests/test_qt_compat.py
araviq6/tests/test_videostream.py
araviq6/util/__init__.py
araviq6/util/controller.py
araviq6/util/testing.py
araviq6/util/tests/__init__.py
araviq6/util/tests/test_controller.py
araviq6-2.1.1.dist-info/LICENSE
araviq6-2.1.1.dist-info/METADATA
araviq6-2.1.1.dist-info/WHEEL
araviq6-2.1.1.dist-info/top_level.txt
araviq6-2.1.1.dist-info/RECORD
